oikonomika/__cli__.py
oikonomika/__init__.py
oikonomika/_version.py
oikonomika/conf/__init__.py
oikonomika/conf/about/__init__.yaml
oikonomika/conf/batch/__init__.yaml
oikonomika/conf/config.yaml
oikonomika/conf/dotenv/__init__.yaml
oikonomika/conf/hconf.yaml
oikonomika/conf/hydra/help/help.yaml
oikonomika/conf/hydra/job_logging/custom.yaml
oikonomika/conf/joblib/__init__.yaml
oikonomika/conf/mode/__init__.yaml
oikonomika/conf/mode/debug.yaml
oikonomika/conf/path/__batch__.yaml
oikonomika/conf/path/__default__.yaml
oikonomika/conf/path/__init__.yaml
oikonomika/conf/project/__init__.yaml
oikonomika/conf/task/__init__.yaml
oikonomika/project.toml
oikonomika/py.typed
oikonomika-0.1.2.dist-info/LICENSE
oikonomika-0.1.2.dist-info/METADATA
oikonomika-0.1.2.dist-info/WHEEL
oikonomika-0.1.2.dist-info/entry_points.txt
oikonomika-0.1.2.dist-info/RECORD
