Metadata-Version: 2.1
Name: oikonomika
Version: 0.1.2
Summary: A Python Library for Economic Analysis
Home-page: https://oikonomika.entelecheia.ai
License: MIT
Author: Young Joon Lee
Author-email: entelecheia@hotmail.com
Requires-Python: >=3.8.1,<3.12
Classifier: License :: OSI Approved :: MIT License
Classifier: Programming Language :: Python :: 3
Classifier: Programming Language :: Python :: 3.9
Classifier: Programming Language :: Python :: 3.10
Classifier: Programming Language :: Python :: 3.11
Requires-Dist: hyfi (>=0.2.20,<0.3.0)
Project-URL: Repository, https://github.com/entelecheia/oikonomika
